LICENSE.txt
MANIFEST.in
README.md
package.json
pylama.ini
requirements.dev.txt
requirements.txt
setup.cfg
setup.py
tox.ini
gobble/__init__.py
gobble/api.py
gobble/cli.py
gobble/config.py
gobble/fiscal.py
gobble/logger.py
gobble/search.py
gobble/snapshot.py
gobble/user.py
os_gobble.egg-info/PKG-INFO
os_gobble.egg-info/SOURCES.txt
os_gobble.egg-info/dependency_links.txt
os_gobble.egg-info/entry_points.txt
os_gobble.egg-info/not-zip-safe
os_gobble.egg-info/requires.txt
os_gobble.egg-info/top_level.txt
tests/__init__.py
tests/fixtures.py
tests/parameters.py
tests/test_api.py
tests/test_configuration.py
tests/test_fiscal.py
tests/test_logger.py
tests/test_search.py
tests/test_snapshots.py
tests/test_user.py