Metadata-Version: 1.1
Name: os-gobble
Version: 0.1.27
Summary: Command line tools for Open-Spending.
Home-page: https://github.com/openspending/gobble
Author: Open Knowledge Foundation
Author-email: info@okfn.org
License: The MIT License (MIT)
Keywords: open spending frictionless data fiscal datapackage
Platform: UNKNOWN
Classifier: Development Status :: 4 - Beta
Classifier: Environment :: Web Environment
Classifier: Intended Audience :: Developers
Classifier: Operating System :: OS Independent
Classifier: Programming Language :: Python :: 2
Classifier: Programming Language :: Python :: 2.7
Classifier: Programming Language :: Python :: 3
Classifier: Programming Language :: Python :: 3.3
Classifier: Programming Language :: Python :: 3.4
Classifier: Programming Language :: Python :: 3.5
Classifier: Topic :: Internet :: WWW/HTTP :: Dynamic Content
Classifier: Topic :: Software Development :: Libraries :: Python Modules
